MANIFEST.in
README.rst
setup.py
django_sortable_column.egg-info/PKG-INFO
django_sortable_column.egg-info/SOURCES.txt
django_sortable_column.egg-info/dependency_links.txt
django_sortable_column.egg-info/top_level.txt
sortable_column/__init__.py
sortable_column/admin.py
sortable_column/models.py
sortable_column/tests.py
sortable_column/views.py
sortable_column/migrations/__init__.py
sortable_column/services/__init__.py
sortable_column/services/url_service.py
sortable_column/templates/sortable_column/sortable_column.html
sortable_column/templatetags/__init__.py
sortable_column/templatetags/sortable_column.py