Metadata-Version: 1.1
Name: django-sortable-column
Version: 0.2.2
Summary: A simple Django templatetag to renders a sortable column to support sorting in tables.
Home-page: https://github.com/weynelucas/django-sortable-column
Author: Lucas Weyne
Author-email: weynelucas@gmail.com
License: BSD License
Platform: UNKNOWN
Classifier: Environment :: Web Environment
Classifier: Framework :: Django
Classifier: Framework :: Django :: 1.8
Classifier: Intended Audience :: Developers
Classifier: License :: OSI Approved :: BSD License
Classifier: Operating System :: OS Independent
Classifier: Programming Language :: Python
Classifier: Programming Language :: Python :: 3
Classifier: Programming Language :: Python :: 3.4
Classifier: Programming Language :: Python :: 3.5
Classifier: Topic :: Internet :: WWW/HTTP
Classifier: Topic :: Internet :: WWW/HTTP :: Dynamic Content
